adi_parser/__init__.py
adi_parser/logger.py
adi_parser/parser.py
adi_parser/dataclasses/__init__.py
adi_parser/dataclasses/header.py
adi_parser/dataclasses/qso_report.py
adi_parser-0.1.1.dist-info/METADATA
adi_parser-0.1.1.dist-info/WHEEL
adi_parser-0.1.1.dist-info/licenses/LICENSE
adi_parser-0.1.1.dist-info/RECORD
