Metadata-Version: 2.1
Name: adi_parser
Version: 0.1.1
Summary: This is a simple utility package, originally to parse .adi files from LoTW, but now from anywhere.
Project-URL: Homepage, https://github.com/JoshuaMaddy/adi_parser
Project-URL: Issues, https://github.com/JoshuaMaddy/adi_parser/issues
Author-email: Joshua Maddy <joshuadcmaddy@gmail.com>
License-File: LICENSE
Classifier: License :: OSI Approved :: MIT License
Classifier: Operating System :: OS Independent
Classifier: Programming Language :: Python :: 3
Requires-Python: >=3.12
Requires-Dist: maidenhead
